LICENSE
tailscale_agent/__init__.py
tailscale_agent/tailscale_agent.py
tailscale_agent-0.7.0.dist-info/LICENSE
tailscale_agent-0.7.0.dist-info/METADATA
tailscale_agent-0.7.0.dist-info/WHEEL
tailscale_agent-0.7.0.dist-info/RECORD
