Metadata-Version: 2.1
Name: tailscale_agent
Version: 0.7.0
Summary: Python Bindings for the TailScal API
Home-page: https://github.com/kevinbringard/tailscale-python-client/
License: MIT
Author: Kevin Bringard
Author-email: kevin.bringard@phreesia.com
Requires-Python: >=3.10,<4.0
Classifier: License :: OSI Approved :: MIT License
Classifier: Programming Language :: Python :: 3
Classifier: Programming Language :: Python :: 3.10
Classifier: Programming Language :: Python :: 3.11
Classifier: Programming Language :: Python :: 3.12
Requires-Dist: requests (>=2.27.1,<3.0.0)
